skivvy/__init__.py
django_skivvy-0.1.12.dist-info/LICENSE
django_skivvy-0.1.12.dist-info/METADATA
django_skivvy-0.1.12.dist-info/WHEEL
django_skivvy-0.1.12.dist-info/top_level.txt
django_skivvy-0.1.12.dist-info/RECORD
