Metadata-Version: 2.1
Name: django-skivvy
Version: 0.1.12
Summary: Write faster integration tests for Django views – with less code.
Home-page: https://github.com/oliverroick/django-skivvy
Author: Oliver Roick
Author-email: oliver.roick@gmail.com
License: AGPL
Platform: UNKNOWN
Classifier: Development Status :: 5 - Production/Stable
Classifier: Environment :: Web Environment
Classifier: Framework :: Django :: 1.11
Classifier: Framework :: Django :: 2.1
Classifier: Framework :: Django :: 2.2
Classifier: Intended Audience :: Developers
Classifier: License :: OSI Approved :: GNU Affero General Public License v3
Classifier: Operating System :: OS Independent
Classifier: Natural Language :: English
Classifier: Programming Language :: Python :: 3.4
Classifier: Programming Language :: Python :: 3.5
Classifier: Programming Language :: Python :: 3.6
Classifier: Programming Language :: Python :: 3.7
Classifier: Topic :: Software Development :: Testing
Classifier: Topic :: Software Development :: Testing :: Mocking
